[
    {
        "text": "Your Favorite\n                        Place for Nurturing Procrastirnation"
    },
    {
        "text": "Start Bootstrap\n                        can help you build better websites\n                        using the Bootstrap\n                        framework! Just download a theme and start customizing, no strings attached!"
    },
    { "text": "We've got what\n                        you need!" },
    {
        "text": "Start Bootstrap\n                        has everything you need to get your\n                        new website up and\n                        running in no time! Choose one of our open source, free to download, and easy to use themes! No\n                        strings attached!"
    },
    { "text": "At Your Service" },
    { "text": "Sturdy\n                            Themes" },
    {
        "text": "Our themes\n                            are updated regularly to keep them bug\n                            free!"
    },
    { "text": "Up to Date\n                        " },
    {
        "text": "All\n                            dependencies are kept current to keep things\n                            fresh."
    },
    { "text": "Ready to\n                            Publish" },
    {
        "text": "You can use\n                            this design as is, or you can make\n                            changes!"
    },
    { "text": "Made with\n                            Love" },
    {
        "text": "Is it\n                            really open source if it's not made with\n                            love?"
    },
    { "text": "Free Download at Start Bootstrap!" },
    { "text": "Let's Get In\n                        Touch!" },
    {
        "text": "Ready to start\n                        your next project with us? Send us a messages and we will\n                        get back to you as soon as possible!"
    },
    { "text": "+1\n                        (555) 123-4567" }
]
